portfolio_stats.py
portfolio_stats-1.0.3.dist-info/LICENSE
portfolio_stats-1.0.3.dist-info/METADATA
portfolio_stats-1.0.3.dist-info/WHEEL
portfolio_stats-1.0.3.dist-info/top_level.txt
portfolio_stats-1.0.3.dist-info/RECORD
