Metadata-Version: 2.1
Name: portfolio-stats
Version: 1.0.3
Summary: Calculate fundamental metrics of a portfolio's individual assets.
Home-page: UNKNOWN
Author: Aung Si
Author-email: aungsi.as99@gmail.com
License: UNKNOWN
Platform: UNKNOWN
Requires-Dist: pandas
Requires-Dist: numpy
